tests/__init__.py
tests/test_tinyspace.py
tinyspace/__init__.py
tinyspace/tinyspace.py
tinyspace/version.py
tinyspace-0.1.1.dist-info/LICENSE
tinyspace-0.1.1.dist-info/METADATA
tinyspace-0.1.1.dist-info/WHEEL
tinyspace-0.1.1.dist-info/top_level.txt
tinyspace-0.1.1.dist-info/RECORD
